small_fish_gui/__init__.py
small_fish_gui/__main__.py
small_fish_gui/hints.py
small_fish_gui/main_menu.py
small_fish_gui/utils.py
small_fish_gui/batch/__init__.py
small_fish_gui/batch/input.py
small_fish_gui/batch/integrity.py
small_fish_gui/batch/output.py
small_fish_gui/batch/pipeline.py
small_fish_gui/batch/prompt.py
small_fish_gui/batch/test.py
small_fish_gui/batch/update.py
small_fish_gui/batch/utils.py
small_fish_gui/gui/__init__.py
small_fish_gui/gui/_napari_widgets.py
small_fish_gui/gui/animation.py
small_fish_gui/gui/layout.py
small_fish_gui/gui/napari_visualiser.py
small_fish_gui/gui/prompts.py
small_fish_gui/gui/testing.ipynb
small_fish_gui/gui/theme.py
small_fish_gui/gui/tooltips.py
small_fish_gui/interface/__init__.py
small_fish_gui/interface/default_settings.py
small_fish_gui/interface/image.py
small_fish_gui/interface/inoutput.py
small_fish_gui/interface/settings.json
small_fish_gui/interface/testing.ipynb
small_fish_gui/interface/testing.py
small_fish_gui/interface/user_settings.py
small_fish_gui/pipeline/__init__.py
small_fish_gui/pipeline/_bigfish_wrapers.py
small_fish_gui/pipeline/_colocalisation.py
small_fish_gui/pipeline/_custom_errors.py
small_fish_gui/pipeline/_preprocess.py
small_fish_gui/pipeline/actions.py
small_fish_gui/pipeline/detection.py
small_fish_gui/pipeline/segmentation.py
small_fish_gui/pipeline/spots.py
small_fish_gui/pipeline/test.py
small_fish_gui/pipeline/utils.py
small_fish_gui-2.1.3.dist-info/METADATA
small_fish_gui-2.1.3.dist-info/WHEEL
small_fish_gui-2.1.3.dist-info/licenses/LICENSE
small_fish_gui-2.1.3.dist-info/RECORD
