Metadata-Version: 2.4
Name: small_fish_gui
Version: 2.1.3
Summary: Small Fish is a python application for the analysis of smFish images. It provides a ready to use graphical interface to combine famous python packages for cell analysis without any need for coding.
Project-URL: Homepage, https://github.com/SmallFishGUI/small_fish_gui
Project-URL: Wiki, https://github.com/SmallFishGUI/small_fish_gui/wiki
Project-URL: Issues, https://github.com/SmallFishGUI/small_fish_gui/issues
Author-email: Slimani Floric <floric.slimani@live.fr>
License-File: LICENSE
Classifier: License :: OSI Approved :: BSD License
Classifier: Operating System :: OS Independent
Classifier: Programming Language :: Python :: 3
Requires-Python: >=3.12
Requires-Dist: af-eraser>=0.1.0
Requires-Dist: aicspylibczi>=3.3.1
Requires-Dist: big-fish-reloaded==0.6.2
Requires-Dist: cellpose>=4.0.6
Requires-Dist: czifile>=2019.7.2
Requires-Dist: freesimplegui>=5.1.1
Requires-Dist: imageio>=2.34.0
Requires-Dist: napari-console>=0.0.9
Requires-Dist: napari-plugin-engine>=0.2.0
Requires-Dist: napari-plugin-manager>=0.1.0a2
Requires-Dist: napari-svg>=0.1.10
Requires-Dist: napari>=0.4.19.post1
Requires-Dist: napari[all]
Requires-Dist: numpy>=1.26
Requires-Dist: openpyxl>=3.1.2
Requires-Dist: pandas>=2.1.1
Requires-Dist: pyarrow>=11.0.0
Requires-Dist: scikit-image>=0.19.1
Requires-Dist: scikit-learn>=1.3.2
Requires-Dist: scipy
